Metadata-Version: 2.1
Name: gtftools
Version: 0.9.0
Summary: gtftools provides a set of functions to compute or extract various features of gene models.
Author: Hong-Dong Li
Author-email: hongdong@csu.edu.cn
License-File: LICENCE
